alt_model_checkpoint/__init__.py
alt_model_checkpoint/test__init__.py
alt_model_checkpoint/keras/__init__.py
alt_model_checkpoint/keras/test__init__.py
alt_model_checkpoint/tensorflow/__init__.py
alt_model_checkpoint/tensorflow/test__init__.py
alt_model_checkpoint-2.0.3.dist-info/LICENSE
alt_model_checkpoint-2.0.3.dist-info/METADATA
alt_model_checkpoint-2.0.3.dist-info/WHEEL
alt_model_checkpoint-2.0.3.dist-info/top_level.txt
alt_model_checkpoint-2.0.3.dist-info/RECORD
