Metadata-Version: 2.1
Name: alt-model-checkpoint
Version: 2.0.3
Summary: An adapter callback for Keras ModelCheckpoint that allows checkpointing an alternate model (often submodel of a multi-GPU model).
Home-page: https://github.com/TextpertAi/alt-model-checkpoint
Author: Ezekiel Victor
Author-email: zekevictor@gmail.com
License: UNKNOWN
Platform: UNKNOWN
Classifier: Programming Language :: Python :: 3
Classifier: License :: OSI Approved :: MIT License
Classifier: Operating System :: OS Independent
Requires-Python: >=3
Requires-Dist: keras
